deepai_api.py
deepai_chat-1.0.1.dist-info/licenses/LICENSE
deepai_chat-1.0.1.dist-info/METADATA
deepai_chat-1.0.1.dist-info/WHEEL
deepai_chat-1.0.1.dist-info/top_level.txt
deepai_chat-1.0.1.dist-info/RECORD
