Metadata-Version: 2.4
Name: deepai-chat
Version: 1.0.1
Summary: Python client library for DeepAI Chat API
Author: DeepAI API Client
License: MIT
Project-URL: Homepage, https://github.com/your-username/deepai-chat
Project-URL: Bug Tracker, https://github.com/your-username/deepai-chat/issues
Keywords: deepai,chat,api,ai,gpt,llm,chatbot
Classifier: Development Status :: 4 - Beta
Classifier: Intended Audience :: Developers
Classifier: License :: OSI Approved :: MIT License
Classifier: Programming Language :: Python :: 3
Classifier: Programming Language :: Python :: 3.7
Classifier: Programming Language :: Python :: 3.8
Classifier: Programming Language :: Python :: 3.9
Classifier: Programming Language :: Python :: 3.10
Classifier: Programming Language :: Python :: 3.11
Classifier: Programming Language :: Python :: 3.12
Classifier: Topic :: Software Development :: Libraries :: Python Modules
Requires-Python: >=3.7
License-File: LICENSE
Requires-Dist: requests>=2.25.0
Dynamic: license-file
